pulumi_azure/__init__.py
pulumi_azure/_inputs.py
pulumi_azure/_utilities.py
pulumi_azure/provider.py
pulumi_azure/pulumi-plugin.json
pulumi_azure/py.typed
pulumi_azure/aadb2c/__init__.py
pulumi_azure/aadb2c/directory.py
pulumi_azure/aadb2c/get_directory.py
pulumi_azure/advisor/__init__.py
pulumi_azure/advisor/get_recommendations.py
pulumi_azure/advisor/outputs.py
pulumi_azure/advisor/suppression.py
pulumi_azure/aifoundry/__init__.py
pulumi_azure/aifoundry/_inputs.py
pulumi_azure/aifoundry/hub.py
pulumi_azure/aifoundry/outputs.py
pulumi_azure/aifoundry/project.py
pulumi_azure/analysisservices/__init__.py
pulumi_azure/analysisservices/_inputs.py
pulumi_azure/analysisservices/outputs.py
pulumi_azure/analysisservices/server.py
pulumi_azure/apimanagement/__init__.py
pulumi_azure/apimanagement/_inputs.py
pulumi_azure/apimanagement/api.py
pulumi_azure/apimanagement/api_diagnostic.py
pulumi_azure/apimanagement/api_operation.py
pulumi_azure/apimanagement/api_operation_policy.py
pulumi_azure/apimanagement/api_operation_tag.py
pulumi_azure/apimanagement/api_policy.py
pulumi_azure/apimanagement/api_release.py
pulumi_azure/apimanagement/api_schema.py
pulumi_azure/apimanagement/api_tag.py
pulumi_azure/apimanagement/api_tag_description.py
pulumi_azure/apimanagement/api_version_set.py
pulumi_azure/apimanagement/authorization_server.py
pulumi_azure/apimanagement/backend.py
pulumi_azure/apimanagement/certificate.py
pulumi_azure/apimanagement/custom_domain.py
pulumi_azure/apimanagement/diagnostic.py
pulumi_azure/apimanagement/email_template.py
pulumi_azure/apimanagement/gateway.py
pulumi_azure/apimanagement/gateway_api.py
pulumi_azure/apimanagement/gateway_certificate_authority.py
pulumi_azure/apimanagement/gateway_host_name_configuration.py
pulumi_azure/apimanagement/get_api.py
pulumi_azure/apimanagement/get_api_version_set.py
pulumi_azure/apimanagement/get_gateway.py
pulumi_azure/apimanagement/get_gateway_host_name_configuration.py
pulumi_azure/apimanagement/get_group.py
pulumi_azure-6.31.0.dist-info/METADATA
pulumi_azure-6.31.0.dist-info/WHEEL
pulumi_azure-6.31.0.dist-info/top_level.txt
pulumi_azure-6.31.0.dist-info/RECORD
