Metadata-Version: 2.4
Name: pulumi_azure
Version: 6.31.0
Summary: A Pulumi package for creating and managing Microsoft Azure cloud resources, based on the Terraform azurerm provider. We recommend using the [Azure Native provider](https://github.com/pulumi/pulumi-azure-native) to provision Azure infrastructure. Azure Native provides complete coverage of Azure resources and same-day access to new resources and resource updates.
License: Apache-2.0
Project-URL: Homepage, https://pulumi.io
Project-URL: Repository, https://github.com/pulumi/pulumi-azure
Keywords: pulumi,azure
Requires-Python: >=3.9
Requires-Dist: parver>=0.2.1
Requires-Dist: pulumi<4.0.0,>=3.165.0
Requires-Dist: semver>=2.8.1
Requires-Dist: typing-extensions<5,>=4.11; python_version < "3.11"
